pdchaosazure/__init__.py
pdchaosazure/auth/__init__.py
pdchaosazure/common/__init__.py
pdchaosazure/common/cleanse.py
pdchaosazure/common/cloud.py
pdchaosazure/common/config.py
pdchaosazure/common/kustolight.py
pdchaosazure/common/compute/__init__.py
pdchaosazure/common/compute/client.py
pdchaosazure/common/compute/command.py
pdchaosazure/common/monitor/__init__.py
pdchaosazure/common/monitor/client.py
pdchaosazure/common/resources/__init__.py
pdchaosazure/common/resources/graph.py
pdchaosazure/common/resources/query.py
pdchaosazure/common/scripts/burn_io.ps1
pdchaosazure/common/scripts/burn_io.sh
pdchaosazure/common/scripts/fill_disk.ps1
pdchaosazure/common/scripts/fill_disk.sh
pdchaosazure/common/scripts/network_latency.sh
pdchaosazure/common/scripts/stress_cpu.ps1
pdchaosazure/common/scripts/stress_cpu.sh
pdchaosazure/monitor/__init__.py
pdchaosazure/monitor/probes.py
pdchaosazure/vm/__init__.py
pdchaosazure/vm/actions.py
pdchaosazure/vm/constants.py
pdchaosazure/vm/fetcher.py
pdchaosazure/vm/probes.py
pdchaosazure/vmss/__init__.py
pdchaosazure/vmss/actions.py
pdchaosazure/vmss/constants.py
pdchaosazure/vmss/fetcher.py
pdchaosazure/vmss/probes.py
pdchaosazure/vmss/records.py
pdchaosazure/webapp/__init__.py
pdchaosazure/webapp/actions.py
pdchaosazure/webapp/client.py
pdchaosazure/webapp/constants.py
pdchaosazure/webapp/fetcher.py
pdchaosazure/webapp/probes.py
tests/auth/__init__.py
tests/auth/test_init.py
tests/common/__init__.py
tests/common/test_cloud.py
tests/common/test_config.py
tests/common/test_kustolight.py
tests/common/compute/__init__.py
tests/common/compute/test_command.py
tests/common/compute/test_compute_client.py
proofdock_chaos_azure-1.1.6.dist-info/LICENSE
proofdock_chaos_azure-1.1.6.dist-info/METADATA
proofdock_chaos_azure-1.1.6.dist-info/WHEEL
proofdock_chaos_azure-1.1.6.dist-info/top_level.txt
proofdock_chaos_azure-1.1.6.dist-info/RECORD
