Metadata-Version: 2.1
Name: proofdock-chaos-azure
Version: 1.1.6
Summary: Extend the Chaos Toolkit and the Chaos Engineering Platform with capabilities for Microsoft Azure
Home-page: https://www.proofdock.io
Author: Proofdock
Author-email: hello@proofdock.io
License: Apache License Version 2.0
Platform: UNKNOWN
Classifier: Development Status :: 5 - Production/Stable
Classifier: Intended Audience :: Developers
Classifier: License :: Freely Distributable
Classifier: Operating System :: OS Independent
Classifier: License :: OSI Approved :: Apache Software License
Classifier: Programming Language :: Python
Classifier: Programming Language :: Python :: 3
Classifier: Programming Language :: Python :: 3.5
Classifier: Programming Language :: Python :: 3.6
Classifier: Programming Language :: Python :: 3.7
Classifier: Programming Language :: Python :: 3.8
Classifier: Programming Language :: Python :: Implementation
Classifier: Programming Language :: Python :: Implementation :: CPython
Requires-Python: >=3.5.*
License-File: LICENSE
Requires-Dist: azure-identity (==1.5.0)
Requires-Dist: azure-mgmt-compute (==18.1.0)
Requires-Dist: azure-mgmt-resourcegraph (==7.0.0)
Requires-Dist: azure-mgmt-web (==1.0.0)
Requires-Dist: azure-mgmt-monitor (==2.0.0)
Requires-Dist: msrestazure (==0.6.4)
Requires-Dist: dateparser
Requires-Dist: jmespath
Requires-Dist: chaostoolkit-lib (>==1.1.2)
Requires-Dist: requests
